{
  "system_id": "JarvisNext v4.0",
  "last_update": "2026-07-20T06:11:59.847Z",
  "developer": "Salvador Duarte",
  "health_status": {
    "jhi_score": "100/100",
    "active_databases": [
      "auditor_history.sqlite",
      "jos_historico.sqlite"
    ]
  },
  "narrative": {
    "summary": "Concluida com sucesso a missao de auto-otimizacao H003: Rodar o DocGenerator, rastrear a integracao do Tasker/mobile_voice, testar a esteira de auto-cura de 5 niveis e atualizar a nuvem.",
    "next_milestone": "Aguardando novo comando de missao para execucao estruturada."
  },
  "git_state": {
    "branch": "main",
    "latest_commit": "69e975b"
  }
}